setup.py
asyncio_nats_client.egg-info/PKG-INFO
asyncio_nats_client.egg-info/SOURCES.txt
asyncio_nats_client.egg-info/dependency_links.txt
asyncio_nats_client.egg-info/top_level.txt
asyncio_nats_client.egg-info/zip-safe
nats/__init__.py
nats/aio/__init__.py
nats/aio/client.py
nats/aio/errors.py
nats/aio/nuid.py
nats/aio/utils.py
nats/protocol/__init__.py
nats/protocol/parser.py