Metadata-Version: 1.1
Name: asyncio-nats-client
Version: 0.7.0
Summary: NATS client for Python Asyncio
Home-page: https://github.com/nats-io/asyncio-nats
Author: Waldemar Quevedo
Author-email: wally@synadia.com
License: Apache 2 License
Platform: UNKNOWN
Classifier: Intended Audience :: Developers
Classifier: Programming Language :: Python
Classifier: Programming Language :: Python :: 3
Classifier: Programming Language :: Python :: 3.4
Classifier: Programming Language :: Python :: 3.5
Classifier: Programming Language :: Python :: 3.6
